{"directed": false, "multigraph": false, "graph": {}, "nodes": [{"id": "A_import"}, {"id": "B_import"}, {"id": "C_import"}, {"id": "D_import"}, {"id": "E_import"}, {"id": "F_import"}, {"id": "G_import"}, {"id": "N_exp"}, {"id": "R_exp"}, {"id": "U_exp"}, {"id": "V_exp"}, {"id": "W_exp"}, {"id": "X_exp"}, {"id": "R_A_B__G_H"}, {"id": "R_C_H__I"}, {"id": "R_C_D__J"}, {"id": "R_I__P"}, {"id": "R_J__Q"}, {"id": "R_E__M"}, {"id": "R_F_M__N"}, {"id": "R_N__T"}, {"id": "R_N__U"}, {"id": "R_H__K"}, {"id": "R_G_K__L"}, {"id": "R_K__O"}, {"id": "R_L__W"}, {"id": "R_O_P__R"}, {"id": "R_P_Q__S"}, {"id": "R_S_T__V_X"}, {"id": "A_C"}, {"id": "B_C"}, {"id": "C_C"}, {"id": "D_C"}, {"id": "E_C"}, {"id": "F_C"}, {"id": "G_C"}, {"id": "N_C"}, {"id": "R_C"}, {"id": "U_C"}, {"id": "V_C"}, {"id": "W_C"}, {"id": "X_C"}, {"id": "H_C"}, {"id": "I_C"}, {"id": "J_C"}, {"id": "P_C"}, {"id": "Q_C"}, {"id": "M_C"}, {"id": "T_C"}, {"id": "K_C"}, {"id": "L_C"}, {"id": "O_C"}, {"id": "S_C"}], "edges": [{"weight": true, "source": "A_import", "target": "A_C"}, {"weight": true, "source": "B_import", "target": "B_C"}, {"weight": true, "source": "C_import", "target": "C_C"}, {"weight": true, "source": "D_import", "target": "D_C"}, {"weight": true, "source": "E_import", "target": "E_C"}, {"weight": true, "source": "F_import", "target": "F_C"}, {"weight": true, "source": "G_import", "target": "G_C"}, {"weight": true, "source": "N_exp", "target": "N_C"}, {"weight": true, "source": "R_exp", "target": "R_C"}, {"weight": true, "source": "U_exp", "target": "U_C"}, {"weight": true, "source": "V_exp", "target": "V_C"}, {"weight": true, "source": "W_exp", "target": "W_C"}, {"weight": true, "source": "X_exp", "target": "X_C"}, {"weight": true, "source": "R_A_B__G_H", "target": "A_C"}, {"weight": true, "source": "R_A_B__G_H", "target": "B_C"}, {"weight": true, "source": "R_A_B__G_H", "target": "G_C"}, {"weight": true, "source": "R_A_B__G_H", "target": "H_C"}, {"weight": true, "source": "R_C_H__I", "target": "C_C"}, {"weight": true, "source": "R_C_H__I", "target": "H_C"}, {"weight": true, "source": "R_C_H__I", "target": "I_C"}, {"weight": true, "source": "R_C_D__J", "target": "C_C"}, {"weight": true, "source": "R_C_D__J", "target": "D_C"}, {"weight": true, "source": "R_C_D__J", "target": "J_C"}, {"weight": true, "source": "R_I__P", "target": "I_C"}, {"weight": true, "source": "R_I__P", "target": "P_C"}, {"weight": true, "source": "R_J__Q", "target": "J_C"}, {"weight": true, "source": "R_J__Q", "target": "Q_C"}, {"weight": true, "source": "R_E__M", "target": "E_C"}, {"weight": true, "source": "R_E__M", "target": "M_C"}, {"weight": true, "source": "R_F_M__N", "target": "F_C"}, {"weight": true, "source": "R_F_M__N", "target": "N_C"}, {"weight": true, "source": "R_F_M__N", "target": "M_C"}, {"weight": true, "source": "R_N__T", "target": "N_C"}, {"weight": true, "source": "R_N__T", "target": "T_C"}, {"weight": true, "source": "R_N__U", "target": "N_C"}, {"weight": true, "source": "R_N__U", "target": "U_C"}, {"weight": true, "source": "R_H__K", "target": "H_C"}, {"weight": true, "source": "R_H__K", "target": "K_C"}, {"weight": true, "source": "R_G_K__L", "target": "G_C"}, {"weight": true, "source": "R_G_K__L", "target": "K_C"}, {"weight": true, "source": "R_G_K__L", "target": "L_C"}, {"weight": true, "source": "R_K__O", "target": "K_C"}, {"weight": true, "source": "R_K__O", "target": "O_C"}, {"weight": true, "source": "R_L__W", "target": "W_C"}, {"weight": true, "source": "R_L__W", "target": "L_C"}, {"weight": true, "source": "R_O_P__R", "target": "R_C"}, {"weight": true, "source": "R_O_P__R", "target": "P_C"}, {"weight": true, "source": "R_O_P__R", "target": "O_C"}, {"weight": true, "source": "R_P_Q__S", "target": "P_C"}, {"weight": true, "source": "R_P_Q__S", "target": "Q_C"}, {"weight": true, "source": "R_P_Q__S", "target": "S_C"}, {"weight": true, "source": "R_S_T__V_X", "target": "V_C"}, {"weight": true, "source": "R_S_T__V_X", "target": "X_C"}, {"weight": true, "source": "R_S_T__V_X", "target": "T_C"}, {"weight": true, "source": "R_S_T__V_X", "target": "S_C"}]}