[{"map_name":"new_map","map_id":"tFgHy2vKNJV5","map_description":"","homepage":"https://escher.github.io","schema":"https://escher.github.io/escher/jsonschema/1-0-0#"},{"reactions":{"3":{"name":"External A exchange","bigg_id":"A_E_ex","reversibility":true,"label_x":-466.0209303687584,"label_y":8.991430722150767,"gene_reaction_rule":"","genes":[],"metabolites":[{"bigg_id":"A_E","coefficient":-1}],"segments":{"9":{"from_node_id":"14","to_node_id":"13","b1":null,"b2":null},"10":{"from_node_id":"15","to_node_id":"14","b1":null,"b2":null},"11":{"from_node_id":"12","to_node_id":"13","b1":{"x":-354.0210833974876,"y":48.853678992586566},"b2":{"x":-299.7712172976256,"y":48.73314622921785}}}},"4":{"name":"External B exchange","bigg_id":"B_E_ex","reversibility":true,"label_x":-468.7699232886803,"label_y":156.88596197215077,"gene_reaction_rule":"","genes":[],"metabolites":[{"bigg_id":"B_E","coefficient":-1}],"segments":{"12":{"from_node_id":"18","to_node_id":"17","b1":null,"b2":null},"13":{"from_node_id":"19","to_node_id":"18","b1":null,"b2":null},"14":{"from_node_id":"16","to_node_id":"17","b1":{"x":-356.77007631740946,"y":196.74821024258654},"b2":{"x":-302.52021021754746,"y":196.62767747921788}}}},"6":{"name":"External C exchange","bigg_id":"C_E_ex","reversibility":true,"label_x":-474.23926024789887,"label_y":306.47895973360136,"gene_reaction_rule":"","genes":[],"metabolites":[{"bigg_id":"C_E","coefficient":-1}],"segments":{"18":{"from_node_id":"26","to_node_id":"25","b1":null,"b2":null},"19":{"from_node_id":"27","to_node_id":"26","b1":null,"b2":null},"20":{"from_node_id":"24","to_node_id":"25","b1":{"x":-362.24954154187986,"y":345.3499005019223},"b2":{"x":-308.00853767411326,"y":344.36197367420317}}}},"7":{"name":"External D exchange","bigg_id":"D_E_ex","reversibility":true,"label_x":-473.139681390477,"label_y":447.77598732149204,"gene_reaction_rule":"","genes":[],"metabolites":[{"bigg_id":"D_E","coefficient":-1}],"segments":{"21":{"from_node_id":"30","to_node_id":"29","b1":null,"b2":null},"22":{"from_node_id":"31","to_node_id":"30","b1":null,"b2":null},"23":{"from_node_id":"28","to_node_id":"29","b1":{"x":-361.149962684458,"y":486.64692808981295},"b2":{"x":-306.9089588166914,"y":485.65900126209374}}}},"8":{"name":"External F exchange","bigg_id":"F_E_ex","reversibility":true,"label_x":-475.16879516000824,"label_y":757.599717790242,"gene_reaction_rule":"","genes":[],"metabolites":[{"bigg_id":"F_E","coefficient":-1}],"segments":{"24":{"from_node_id":"34","to_node_id":"33","b1":null,"b2":null},"25":{"from_node_id":"35","to_node_id":"34","b1":null,"b2":null},"26":{"from_node_id":"32","to_node_id":"33","b1":{"x":-363.17907645398924,"y":796.470658558563},"b2":{"x":-308.93807258622263,"y":795.4827317308437}}}},"10":{"name":"External A import","bigg_id":"A_import","reversibility":true,"label_x":-116.0213623046875,"label_y":8.602615356445312,"gene_reaction_rule":"","genes":[],"metabolites":[{"bigg_id":"A_C","coefficient":1},{"bigg_id":"A_E","coefficient":-1}],"segments":{"31":{"from_node_id":"41","to_node_id":"40","b1":null,"b2":null},"32":{"from_node_id":"42","to_node_id":"41","b1":null,"b2":null},"33":{"from_node_id":"42","to_node_id":"43","b1":{"x":-4.0213623046875,"y":48.60261535644531},"b2":{"x":50.2286376953125,"y":48.60261535644531}},"34":{"from_node_id":"12","to_node_id":"40","b1":{"x":-128.0213623046875,"y":48.60261535644531},"b2":{"x":-182.2713623046875,"y":48.60261535644531}}}},"11":{"name":"External B import","bigg_id":"B_import","reversibility":true,"label_x":-118.77035522460938,"label_y":156.4971466064453,"gene_reaction_rule":"","genes":[],"metabolites":[{"bigg_id":"B_C","coefficient":1},{"bigg_id":"B_E","coefficient":-1}],"segments":{"35":{"from_node_id":"45","to_node_id":"44","b1":null,"b2":null},"36":{"from_node_id":"46","to_node_id":"45","b1":null,"b2":null},"37":{"from_node_id":"46","to_node_id":"47","b1":{"x":-6.770355224609375,"y":196.4971466064453},"b2":{"x":47.479644775390625,"y":196.4971466064453}},"38":{"from_node_id":"16","to_node_id":"44","b1":{"x":-130.77035522460938,"y":196.4971466064453},"b2":{"x":-185.02035522460938,"y":196.4971466064453}}}},"12":{"name":"External C import","bigg_id":"C_import","reversibility":true,"label_x":-124.26828002929688,"label_y":303.29209899902344,"gene_reaction_rule":"","genes":[],"metabolites":[{"bigg_id":"C_C","coefficient":1},{"bigg_id":"C_E","coefficient":-1}],"segments":{"39":{"from_node_id":"49","to_node_id":"48","b1":null,"b2":null},"40":{"from_node_id":"50","to_node_id":"49","b1":null,"b2":null},"41":{"from_node_id":"50","to_node_id":"51","b1":{"x":-12.268280029296875,"y":343.29209899902344},"b2":{"x":40.502227783203125,"y":343.2920684814453}},"42":{"from_node_id":"24","to_node_id":"48","b1":{"x":-136.26828002929688,"y":343.29209899902344},"b2":{"x":-190.51828002929688,"y":343.29209899902344}}}},"13":{"name":"External D import","bigg_id":"D_import","reversibility":true,"label_x":-123.168701171875,"label_y":444.58912658691406,"gene_reaction_rule":"","genes":[],"metabolites":[{"bigg_id":"D_C","coefficient":1},{"bigg_id":"D_E","coefficient":-1}],"segments":{"43":{"from_node_id":"53","to_node_id":"52","b1":null,"b2":null},"44":{"from_node_id":"54","to_node_id":"53","b1":null,"b2":null},"45":{"from_node_id":"54","to_node_id":"55","b1":{"x":-11.168701171875,"y":484.58912658691406},"b2":{"x":43.081298828125,"y":484.58912658691406}},"46":{"from_node_id":"28","to_node_id":"52","b1":{"x":-135.168701171875,"y":484.58912658691406},"b2":{"x":-189.418701171875,"y":484.58912658691406}}}},"14":{"name":"External F import","bigg_id":"F_import","reversibility":true,"label_x":-125.19781494140625,"label_y":754.4128570556641,"gene_reaction_rule":"","genes":[],"metabolites":[{"bigg_id":"F_C","coefficient":1},{"bigg_id":"F_E","coefficient":-1}],"segments":{"47":{"from_node_id":"57","to_node_id":"56","b1":null,"b2":null},"48":{"from_node_id":"58","to_node_id":"57","b1":null,"b2":null},"49":{"from_node_id":"58","to_node_id":"59","b1":{"x":-13.19781494140625,"y":794.4128570556641},"b2":{"x":41.05218505859375,"y":794.4128570556641}},"50":{"from_node_id":"32","to_node_id":"56","b1":{"x":-137.19781494140625,"y":794.4128570556641},"b2":{"x":-191.44781494140625,"y":794.4128570556641}}}},"16":{"name":"Reaction A+B<->G+H","bigg_id":"R_A_B__G_H","reversibility":true,"label_x":236.9373779296875,"label_y":14.520013809204102,"gene_reaction_rule":"g001","genes":[{"name":"","bigg_id":"g001"}],"metabolites":[{"bigg_id":"A_C","coefficient":-1},{"bigg_id":"B_C","coefficient":-1},{"bigg_id":"G_C","coefficient":1},{"bigg_id":"H_C","coefficient":1}],"segments":{"57":{"from_node_id":"67","to_node_id":"66","b1":null,"b2":null},"58":{"from_node_id":"68","to_node_id":"67","b1":null,"b2":null},"59":{"from_node_id":"43","to_node_id":"66","b1":{"x":221.9786376953125,"y":48.60261535644531},"b2":{"x":170.68731689453125,"y":48.60260009765625}},"60":{"from_node_id":"69","to_node_id":"66","b1":{"x":145.49053955078125,"y":116.65266418457031},"b2":{"x":215.68731689453125,"y":66.60260009765625}},"61":{"from_node_id":"68","to_node_id":"70","b1":{"x":440.65692138671875,"y":48.60260772705078},"b2":{"x":592.5440673828125,"y":45.6439208984375}},"62":{"from_node_id":"68","to_node_id":"71","b1":{"x":444.65692138671875,"y":48.60260772705078},"b2":{"x":472.4911244997786,"y":114.53670336776469}}}},"18":{"name":"Reaction C+H<->I","bigg_id":"R_C_H__I","reversibility":true,"label_x":625.7962646484375,"label_y":247.38414001464844,"gene_reaction_rule":"g002 or g003","genes":[{"name":"","bigg_id":"g002"},{"name":"","bigg_id":"g003"}],"metabolites":[{"bigg_id":"C_C","coefficient":-1},{"bigg_id":"H_C","coefficient":-1},{"bigg_id":"I_C","coefficient":1}],"segments":{"68":{"from_node_id":"79","to_node_id":"78","b1":null,"b2":null},"69":{"from_node_id":"80","to_node_id":"79","b1":null,"b2":null},"70":{"from_node_id":"77","to_node_id":"78","b1":{"x":139.36334228515625,"y":263.7145538330078},"b2":{"x":595.6700439453125,"y":305.3841094970703}},"71":{"from_node_id":"81","to_node_id":"78","b1":{"x":619.7135009765625,"y":176.43296813964844},"b2":{"x":550.6700439453125,"y":287.3841094970703}},"72":{"from_node_id":"80","to_node_id":"82","b1":{"x":752.5897216796875,"y":285.90480041503906},"b2":{"x":749.1451416015625,"y":285.90480041503906}}}},"19":{"name":"Reaction C+D<->J","bigg_id":"R_C_D__J","reversibility":true,"label_x":212.0491943359375,"label_y":478.27772521972656,"gene_reaction_rule":"g004","genes":[{"name":"","bigg_id":"g004"}],"metabolites":[{"bigg_id":"C_C","coefficient":-1},{"bigg_id":"D_C","coefficient":-1},{"bigg_id":"J_C","coefficient":1}],"segments":{"73":{"from_node_id":"84","to_node_id":"83","b1":null,"b2":null},"74":{"from_node_id":"85","to_node_id":"84","b1":null,"b2":null},"75":{"from_node_id":"77","to_node_id":"83","b1":{"x":213.36334228515625,"y":343.7145538330078},"b2":{"x":159.11334228515625,"y":423.59938049316406}},"76":{"from_node_id":"86","to_node_id":"83","b1":{"x":141.31329345703125,"y":404.3678741455078},"b2":{"x":204.11334228515625,"y":441.59938049316406}},"77":{"from_node_id":"85","to_node_id":"87","b1":{"x":337.36334228515625,"y":423.59938049316406},"b2":{"x":452.26666259765625,"y":425.07875061035156}}}},"20":{"name":"External E exchange","bigg_id":"E_E_ex","reversibility":true,"label_x":-469.795654296875,"label_y":603.9072418212891,"gene_reaction_rule":"","genes":[],"metabolites":[{"bigg_id":"E_E","coefficient":-1}],"segments":{"78":{"from_node_id":"90","to_node_id":"89","b1":null,"b2":null},"79":{"from_node_id":"91","to_node_id":"90","b1":null,"b2":null},"80":{"from_node_id":"88","to_node_id":"89","b1":{"x":-357.795654296875,"y":643.9072418212891},"b2":{"x":-303.545654296875,"y":643.9072418212891}}}},"21":{"name":"External E import","bigg_id":"E_import","reversibility":true,"label_x":-119.795654296875,"label_y":603.9072418212891,"gene_reaction_rule":"","genes":[],"metabolites":[{"bigg_id":"E_C","coefficient":1},{"bigg_id":"E_E","coefficient":-1}],"segments":{"81":{"from_node_id":"94","to_node_id":"93","b1":null,"b2":null},"82":{"from_node_id":"95","to_node_id":"94","b1":null,"b2":null},"83":{"from_node_id":"95","to_node_id":"96","b1":{"x":-7.795654296875,"y":643.9072418212891},"b2":{"x":46.454345703125,"y":643.9072418212891}},"84":{"from_node_id":"92","to_node_id":"93","b1":{"x":-131.795654296875,"y":643.9072418212891},"b2":{"x":-186.045654296875,"y":643.9072418212891}}}},"22":{"name":"Reaction E<->M","bigg_id":"R_E__M","reversibility":true,"label_x":230.204345703125,"label_y":603.9072418212891,"gene_reaction_rule":"g005","genes":[{"name":"","bigg_id":"g005"}],"metabolites":[{"bigg_id":"E_C","coefficient":-1},{"bigg_id":"M_C","coefficient":1}],"segments":{"85":{"from_node_id":"98","to_node_id":"97","b1":null,"b2":null},"86":{"from_node_id":"99","to_node_id":"98","b1":null,"b2":null},"87":{"from_node_id":"96","to_node_id":"97","b1":{"x":218.204345703125,"y":643.9072418212891},"b2":{"x":163.954345703125,"y":643.9072418212891}},"88":{"from_node_id":"99","to_node_id":"100","b1":{"x":342.204345703125,"y":643.9072418212891},"b2":{"x":396.454345703125,"y":643.9072418212891}}}},"23":{"name":"Reaction F+M->N","bigg_id":"R_F_M__N","reversibility":false,"label_x":547.65869140625,"label_y":700.0648956298828,"gene_reaction_rule":"g006 and g007","genes":[{"name":"","bigg_id":"g006"},{"name":"","bigg_id":"g007"}],"metabolites":[{"bigg_id":"F_C","coefficient":-1},{"bigg_id":"M_C","coefficient":-1},{"bigg_id":"N_C","coefficient":1}],"segments":{"89":{"from_node_id":"102","to_node_id":"101","b1":null,"b2":null},"90":{"from_node_id":"103","to_node_id":"102","b1":null,"b2":null},"91":{"from_node_id":"104","to_node_id":"101","b1":{"x":138.15185546875,"y":714.9159698486328},"b2":{"x":526.40869140625,"y":758.0648956298828}},"92":{"from_node_id":"100","to_node_id":"101","b1":{"x":568.204345703125,"y":643.9072418212891},"b2":{"x":481.40869140625,"y":740.0648956298828}},"93":{"from_node_id":"103","to_node_id":"105","b1":{"x":659.65869140625,"y":740.0648956298828},"b2":{"x":764.20654296875,"y":743.0235748291016}}}},"24":{"name":"N export","bigg_id":"N_exp","reversibility":false,"label_x":837.9564208984375,"label_y":857.0147857666016,"gene_reaction_rule":"","genes":[],"metabolites":[{"bigg_id":"N_C","coefficient":-1},{"bigg_id":"N_E","coefficient":1}],"segments":{"94":{"from_node_id":"107","to_node_id":"106","b1":null,"b2":null},"95":{"from_node_id":"108","to_node_id":"107","b1":null,"b2":null},"96":{"from_node_id":"105","to_node_id":"106","b1":{"x":822.95654296875,"y":856.0235748291016},"b2":{"x":822.95654296875,"y":727.8061676025391}},"97":{"from_node_id":"108","to_node_id":"109","b1":{"x":822.9564208984375,"y":909.0148468017578},"b2":{"x":822.95654296875,"y":873.0244903564453}}}},"25":{"name":"External N exchange","bigg_id":"N_E_ex","reversibility":true,"label_x":837.95654296875,"label_y":1048.7245025634766,"gene_reaction_rule":"","genes":[],"metabolites":[{"bigg_id":"N_E","coefficient":-1}],"segments":{"98":{"from_node_id":"111","to_node_id":"110","b1":null,"b2":null},"99":{"from_node_id":"112","to_node_id":"111","b1":null,"b2":null},"100":{"from_node_id":"109","to_node_id":"110","b1":{"x":822.95654296875,"y":1044.7744903564453},"b2":{"x":822.95654296875,"y":922.4745025634766}}}},"26":{"name":"External G import","bigg_id":"G_import","reversibility":true,"label_x":666.2940673828125,"label_y":-30.595138549804688,"gene_reaction_rule":"","genes":[],"metabolites":[{"bigg_id":"G_C","coefficient":1},{"bigg_id":"G_E","coefficient":-1}],"segments":{"101":{"from_node_id":"114","to_node_id":"113","b1":null,"b2":null},"102":{"from_node_id":"115","to_node_id":"114","b1":null,"b2":null},"103":{"from_node_id":"115","to_node_id":"70","b1":{"x":651.2940673828125,"y":21.404861450195312},"b2":{"x":651.2940673828125,"y":-13.1060791015625}},"104":{"from_node_id":"116","to_node_id":"113","b1":{"x":651.2940673828125,"y":-28.62769317626953},"b2":{"x":651.2940673828125,"y":-156.8451385498047}}}},"27":{"name":"External G exchange","bigg_id":"G_E_ex","reversibility":true,"label_x":666.2940673828125,"label_y":-226.74285125732422,"gene_reaction_rule":"","genes":[],"metabolites":[{"bigg_id":"G_E","coefficient":-1}],"segments":{"105":{"from_node_id":"118","to_node_id":"117","b1":null,"b2":null},"106":{"from_node_id":"119","to_node_id":"118","b1":null,"b2":null},"107":{"from_node_id":"116","to_node_id":"117","b1":{"x":651.2940673828125,"y":-254.62769317626953},"b2":{"x":651.2940673828125,"y":-120.49285125732422}}}},"28":{"name":"Reaction H<->K","bigg_id":"R_H__K","reversibility":true,"label_x":631.7135009765625,"label_y":136.43296813964844,"gene_reaction_rule":"g011 or g012","genes":[{"name":"","bigg_id":"g011"},{"name":"","bigg_id":"g012"}],"metabolites":[{"bigg_id":"H_C","coefficient":-1},{"bigg_id":"K_C","coefficient":1}],"segments":{"108":{"from_node_id":"121","to_node_id":"120","b1":null,"b2":null},"109":{"from_node_id":"122","to_node_id":"121","b1":null,"b2":null},"110":{"from_node_id":"81","to_node_id":"120","b1":{"x":619.7135009765625,"y":176.43296813964844},"b2":{"x":565.4635009765625,"y":176.43296813964844}},"111":{"from_node_id":"122","to_node_id":"123","b1":{"x":743.7135009765625,"y":176.43296813964844},"b2":{"x":797.9635009765625,"y":176.43296813964844}}}},"29":{"name":"Reaction G+K<->L","bigg_id":"R_G_K__L","reversibility":true,"label_x":943.46044921875,"label_y":7.123260498046875,"gene_reaction_rule":"g006 and g007","genes":[{"name":"","bigg_id":"g006"},{"name":"","bigg_id":"g007"}],"metabolites":[{"bigg_id":"G_C","coefficient":-1},{"bigg_id":"K_C","coefficient":-1},{"bigg_id":"L_C","coefficient":1}],"segments":{"112":{"from_node_id":"125","to_node_id":"124","b1":null,"b2":null},"113":{"from_node_id":"126","to_node_id":"125","b1":null,"b2":null},"114":{"from_node_id":"70","to_node_id":"124","b1":{"x":764.2940673828125,"y":45.6439208984375},"b2":{"x":877.21044921875,"y":47.123260498046875}},"115":{"from_node_id":"127","to_node_id":"124","b1":{"x":896.3941650390625,"y":95.94178771972656},"b2":{"x":922.21044921875,"y":65.12326049804688}},"116":{"from_node_id":"126","to_node_id":"128","b1":{"x":1055.46044921875,"y":47.123260498046875},"b2":{"x":1057.9332275390625,"y":45.6439208984375}}}},"30":{"name":"Reaction J<->Q","bigg_id":"R_J__Q","reversibility":true,"label_x":636.0166625976562,"label_y":385.07875061035156,"gene_reaction_rule":"g010","genes":[{"name":"","bigg_id":"g010"}],"metabolites":[{"bigg_id":"J_C","coefficient":-1},{"bigg_id":"Q_C","coefficient":1}],"segments":{"117":{"from_node_id":"130","to_node_id":"129","b1":null,"b2":null},"118":{"from_node_id":"131","to_node_id":"130","b1":null,"b2":null},"119":{"from_node_id":"87","to_node_id":"129","b1":{"x":624.0166625976562,"y":425.07875061035156},"b2":{"x":569.7666625976562,"y":425.07875061035156}},"120":{"from_node_id":"131","to_node_id":"132","b1":{"x":748.0166625976562,"y":425.07875061035156},"b2":{"x":802.2666625976562,"y":425.07875061035156}}}},"31":{"name":"Reaction I<->P","bigg_id":"R_I__P","reversibility":true,"label_x":866.3243408203125,"label_y":254.78089904785156,"gene_reaction_rule":"g008","genes":[{"name":"","bigg_id":"g008"}],"metabolites":[{"bigg_id":"I_C","coefficient":-1},{"bigg_id":"P_C","coefficient":1}],"segments":{"121":{"from_node_id":"134","to_node_id":"133","b1":null,"b2":null},"122":{"from_node_id":"135","to_node_id":"134","b1":null,"b2":null},"123":{"from_node_id":"82","to_node_id":"133","b1":{"x":920.8951416015625,"y":285.90480041503906},"b2":{"x":801.5537109375,"y":285.90480041503906}},"124":{"from_node_id":"135","to_node_id":"136","b1":{"x":979.8037109375,"y":285.90480041503906},"b2":{"x":957.1275634765625,"y":284.4254608154297}}}},"32":{"name":"Reaction P+Q->S","bigg_id":"R_P_Q__S","reversibility":false,"label_x":1127.5634765625,"label_y":321.35157775878906,"gene_reaction_rule":"g016","genes":[{"name":"","bigg_id":"g016"}],"metabolites":[{"bigg_id":"P_C","coefficient":-1},{"bigg_id":"Q_C","coefficient":-1},{"bigg_id":"S_C","coefficient":1}],"segments":{"125":{"from_node_id":"138","to_node_id":"137","b1":null,"b2":null},"126":{"from_node_id":"139","to_node_id":"138","b1":null,"b2":null},"127":{"from_node_id":"136","to_node_id":"137","b1":{"x":1128.8775634765625,"y":284.4254608154297},"b2":{"x":1061.3134765625,"y":361.35157775878906}},"128":{"from_node_id":"140","to_node_id":"137","b1":{"x":900.0164794921875,"y":345.07875061035156},"b2":{"x":1106.3134765625,"y":379.35157775878906}},"129":{"from_node_id":"139","to_node_id":"141","b1":{"x":1239.5634765625,"y":361.35157775878906},"b2":{"x":1274.58203125,"y":359.8722686767578}}}},"33":{"name":"Reaction N->U","bigg_id":"R_N__U","reversibility":false,"label_x":952.39453125,"label_y":698.5855255126953,"gene_reaction_rule":"g011 or g013","genes":[{"name":"","bigg_id":"g011"},{"name":"","bigg_id":"g013"}],"metabolites":[{"bigg_id":"N_C","coefficient":-1},{"bigg_id":"U_C","coefficient":1}],"segments":{"130":{"from_node_id":"143","to_node_id":"142","b1":null,"b2":null},"131":{"from_node_id":"144","to_node_id":"143","b1":null,"b2":null},"132":{"from_node_id":"105","to_node_id":"142","b1":{"x":935.95654296875,"y":743.0235748291016},"b2":{"x":886.14453125,"y":738.5855255126953}},"133":{"from_node_id":"144","to_node_id":"145","b1":{"x":1064.39453125,"y":738.5855255126953},"b2":{"x":1634.9375,"y":743.0235748291016}}}},"34":{"name":"Reaction N<->T","bigg_id":"R_N__T","reversibility":true,"label_x":992.3370361328125,"label_y":500.35276794433594,"gene_reaction_rule":"g011 or g012","genes":[{"name":"","bigg_id":"g011"},{"name":"","bigg_id":"g012"}],"metabolites":[{"bigg_id":"N_C","coefficient":-1},{"bigg_id":"T_C","coefficient":1}],"segments":{"134":{"from_node_id":"147","to_node_id":"146","b1":null,"b2":null},"135":{"from_node_id":"148","to_node_id":"147","b1":null,"b2":null},"136":{"from_node_id":"105","to_node_id":"146","b1":{"x":935.95654296875,"y":743.0235748291016},"b2":{"x":911.29345703125,"y":538.8733673095703}},"137":{"from_node_id":"148","to_node_id":"149","b1":{"x":1123.5684814453125,"y":537.3940582275391},"b2":{"x":1276.9349365234375,"y":535.9147491455078}}}},"35":{"name":"Reaction L->W","bigg_id":"R_L__W","reversibility":false,"label_x":1241.6832275390625,"label_y":5.6439208984375,"gene_reaction_rule":"g014 and g020","genes":[{"name":"","bigg_id":"g014"},{"name":"","bigg_id":"g020"}],"metabolites":[{"bigg_id":"L_C","coefficient":-1},{"bigg_id":"W_C","coefficient":1}],"segments":{"138":{"from_node_id":"151","to_node_id":"150","b1":null,"b2":null},"139":{"from_node_id":"152","to_node_id":"151","b1":null,"b2":null},"140":{"from_node_id":"128","to_node_id":"150","b1":{"x":1229.6832275390625,"y":45.6439208984375},"b2":{"x":1175.4332275390625,"y":45.6439208984375}},"141":{"from_node_id":"152","to_node_id":"153","b1":{"x":1353.6832275390625,"y":45.6439208984375},"b2":{"x":1648.28955078125,"y":47.123268127441406}}}},"36":{"name":"W export","bigg_id":"W_exp","reversibility":false,"label_x":1813.5855712890625,"label_y":7.123268127441406,"gene_reaction_rule":"g017","genes":[{"name":"","bigg_id":"g017"}],"metabolites":[{"bigg_id":"W_C","coefficient":-1},{"bigg_id":"W_E","coefficient":1}],"segments":{"142":{"from_node_id":"155","to_node_id":"154","b1":null,"b2":null},"143":{"from_node_id":"156","to_node_id":"155","b1":null,"b2":null},"144":{"from_node_id":"153","to_node_id":"154","b1":{"x":1820.03955078125,"y":47.123268127441406},"b2":{"x":1747.3355712890625,"y":47.123268127441406}},"145":{"from_node_id":"156","to_node_id":"157","b1":{"x":1925.5855712890625,"y":47.123268127441406},"b2":{"x":1979.8355712890625,"y":47.123268127441406}}}},"37":{"name":"External W exchange","bigg_id":"W_E_ex","reversibility":true,"label_x":2163.5855712890625,"label_y":7.123268127441406,"gene_reaction_rule":"","genes":[],"metabolites":[{"bigg_id":"W_E","coefficient":-1}],"segments":{"146":{"from_node_id":"159","to_node_id":"158","b1":null,"b2":null},"147":{"from_node_id":"160","to_node_id":"159","b1":null,"b2":null},"148":{"from_node_id":"157","to_node_id":"158","b1":{"x":2151.5855712890625,"y":47.123268127441406},"b2":{"x":2097.3355712890625,"y":47.123268127441406}}}},"38":{"name":"Reaction K->O","bigg_id":"R_K__O","reversibility":false,"label_x":895.112548828125,"label_y":135.94178771972656,"gene_reaction_rule":"g024","genes":[{"name":"","bigg_id":"g024"}],"metabolites":[{"bigg_id":"K_C","coefficient":-1},{"bigg_id":"O_C","coefficient":1}],"segments":{"149":{"from_node_id":"162","to_node_id":"161","b1":null,"b2":null},"150":{"from_node_id":"163","to_node_id":"162","b1":null,"b2":null},"151":{"from_node_id":"127","to_node_id":"161","b1":{"x":970.3941650390625,"y":175.94178771972656},"b2":{"x":828.862548828125,"y":175.94178771972656}},"152":{"from_node_id":"163","to_node_id":"164","b1":{"x":1007.112548828125,"y":175.94178771972656},"b2":{"x":981.4776611328125,"y":175.9418182373047}}}},"39":{"name":"Reaction O+P->R","bigg_id":"R_O_P__R","reversibility":false,"label_x":1178.5418701171875,"label_y":146.2972412109375,"gene_reaction_rule":"g015 and g020","genes":[{"name":"","bigg_id":"g015"},{"name":"","bigg_id":"g020"}],"metabolites":[{"bigg_id":"O_C","coefficient":-1},{"bigg_id":"P_C","coefficient":-1},{"bigg_id":"R_C","coefficient":1}],"segments":{"153":{"from_node_id":"166","to_node_id":"165","b1":null,"b2":null},"154":{"from_node_id":"167","to_node_id":"166","b1":null,"b2":null},"155":{"from_node_id":"164","to_node_id":"165","b1":{"x":1153.2276611328125,"y":175.9418182373047},"b2":{"x":1122.647216796875,"y":178.90049743652344}},"156":{"from_node_id":"168","to_node_id":"165","b1":{"x":1053.070068359375,"y":204.04942321777344},"b2":{"x":1167.647216796875,"y":196.90049743652344}},"157":{"from_node_id":"167","to_node_id":"169","b1":{"x":1357.112548828125,"y":177.42112731933594},"b2":{"x":1648.28955078125,"y":175.9417953491211}}}},"40":{"name":"R export","bigg_id":"R_exp","reversibility":false,"label_x":1788.9073486328125,"label_y":137.42113494873047,"gene_reaction_rule":"g018","genes":[{"name":"","bigg_id":"g018"}],"metabolites":[{"bigg_id":"R_C","coefficient":-1},{"bigg_id":"R_E","coefficient":1}],"segments":{"158":{"from_node_id":"171","to_node_id":"170","b1":null,"b2":null},"159":{"from_node_id":"172","to_node_id":"171","b1":null,"b2":null},"160":{"from_node_id":"169","to_node_id":"170","b1":{"x":1820.03955078125,"y":175.9417953491211},"b2":{"x":1722.6573486328125,"y":177.42113494873047}},"161":{"from_node_id":"172","to_node_id":"173","b1":{"x":1900.9073486328125,"y":177.42113494873047},"b2":{"x":1975.8680419921875,"y":180.37981414794922}}}},"41":{"name":"External R exchange","bigg_id":"R_E_ex","reversibility":true,"label_x":2164.0562744140625,"label_y":138.90050506591797,"gene_reaction_rule":"","genes":[],"metabolites":[{"bigg_id":"R_E","coefficient":-1}],"segments":{"162":{"from_node_id":"175","to_node_id":"174","b1":null,"b2":null},"163":{"from_node_id":"176","to_node_id":"175","b1":null,"b2":null},"164":{"from_node_id":"173","to_node_id":"174","b1":{"x":2147.6180419921875,"y":180.37981414794922},"b2":{"x":2097.8062744140625,"y":178.90050506591797}}}},"42":{"name":"Reaction S+T->V+X","bigg_id":"R_S_T__V_X","reversibility":false,"label_x":1458.33203125,"label_y":319.8722686767578,"gene_reaction_rule":"g019","genes":[{"name":"","bigg_id":"g019"}],"metabolites":[{"bigg_id":"S_C","coefficient":-1},{"bigg_id":"T_C","coefficient":-1},{"bigg_id":"V_C","coefficient":1},{"bigg_id":"X_C","coefficient":1}],"segments":{"165":{"from_node_id":"178","to_node_id":"177","b1":null,"b2":null},"166":{"from_node_id":"179","to_node_id":"178","b1":null,"b2":null},"167":{"from_node_id":"141","to_node_id":"177","b1":{"x":1446.33203125,"y":359.8722686767578},"b2":{"x":1392.08203125,"y":359.8722686767578}},"168":{"from_node_id":"180","to_node_id":"177","b1":{"x":1374.281982421875,"y":456.02992248535156},"b2":{"x":1437.08203125,"y":377.8722686767578}},"169":{"from_node_id":"179","to_node_id":"181","b1":{"x":1570.33203125,"y":359.8722686767578},"b2":{"x":1648.28955078125,"y":364.31031799316406}},"170":{"from_node_id":"179","to_node_id":"182","b1":{"x":1574.33203125,"y":359.8722686767578},"b2":{"x":1673.28955078125,"y":475.5093536376953}}}},"43":{"name":"V export","bigg_id":"V_exp","reversibility":false,"label_x":1832.03955078125,"label_y":324.31031799316406,"gene_reaction_rule":"g022","genes":[{"name":"","bigg_id":"g022"}],"metabolites":[{"bigg_id":"V_C","coefficient":-1},{"bigg_id":"V_E","coefficient":1}],"segments":{"171":{"from_node_id":"184","to_node_id":"183","b1":null,"b2":null},"172":{"from_node_id":"185","to_node_id":"184","b1":null,"b2":null},"173":{"from_node_id":"181","to_node_id":"183","b1":{"x":1820.03955078125,"y":364.31031799316406},"b2":{"x":1765.78955078125,"y":364.31031799316406}},"174":{"from_node_id":"185","to_node_id":"186","b1":{"x":1944.03955078125,"y":364.31031799316406},"b2":{"x":1998.28955078125,"y":364.31031799316406}}}},"44":{"name":"External V exchange","bigg_id":"V_E_ex","reversibility":true,"label_x":2182.03955078125,"label_y":324.31031799316406,"gene_reaction_rule":"","genes":[],"metabolites":[{"bigg_id":"V_E","coefficient":-1}],"segments":{"175":{"from_node_id":"188","to_node_id":"187","b1":null,"b2":null},"176":{"from_node_id":"189","to_node_id":"188","b1":null,"b2":null},"177":{"from_node_id":"186","to_node_id":"187","b1":{"x":2170.03955078125,"y":364.31031799316406},"b2":{"x":2115.78955078125,"y":364.31031799316406}}}},"47":{"name":"X export","bigg_id":"X_exp","reversibility":false,"label_x":1832.03955078125,"label_y":497.5093536376953,"gene_reaction_rule":"g021","genes":[{"name":"","bigg_id":"g021"}],"metabolites":[{"bigg_id":"X_C","coefficient":-1},{"bigg_id":"X_E","coefficient":1}],"segments":{"188":{"from_node_id":"201","to_node_id":"200","b1":null,"b2":null},"189":{"from_node_id":"202","to_node_id":"201","b1":null,"b2":null},"190":{"from_node_id":"182","to_node_id":"200","b1":{"x":1820.03955078125,"y":537.5093536376953},"b2":{"x":1765.78955078125,"y":537.5093536376953}},"191":{"from_node_id":"202","to_node_id":"203","b1":{"x":1944.03955078125,"y":537.5093536376953},"b2":{"x":1998.28955078125,"y":537.5093536376953}}}},"48":{"name":"External X exchange","bigg_id":"X_E_ex","reversibility":true,"label_x":2182.03955078125,"label_y":497.5093536376953,"gene_reaction_rule":"","genes":[],"metabolites":[{"bigg_id":"X_E","coefficient":-1}],"segments":{"192":{"from_node_id":"205","to_node_id":"204","b1":null,"b2":null},"193":{"from_node_id":"206","to_node_id":"205","b1":null,"b2":null},"194":{"from_node_id":"203","to_node_id":"204","b1":{"x":2170.03955078125,"y":537.5093536376953},"b2":{"x":2115.78955078125,"y":537.5093536376953}}}},"49":{"name":"U export","bigg_id":"U_exp","reversibility":false,"label_x":1818.6875,"label_y":703.0235748291016,"gene_reaction_rule":"g023","genes":[{"name":"","bigg_id":"g023"}],"metabolites":[{"bigg_id":"U_C","coefficient":-1},{"bigg_id":"U_E","coefficient":1}],"segments":{"195":{"from_node_id":"208","to_node_id":"207","b1":null,"b2":null},"196":{"from_node_id":"209","to_node_id":"208","b1":null,"b2":null},"197":{"from_node_id":"145","to_node_id":"207","b1":{"x":1806.6875,"y":743.0235748291016},"b2":{"x":1752.4375,"y":743.0235748291016}},"198":{"from_node_id":"209","to_node_id":"210","b1":{"x":1930.6875,"y":743.0235748291016},"b2":{"x":1984.9375,"y":743.0235748291016}}}},"50":{"name":"External U exchange","bigg_id":"U_E_ex","reversibility":true,"label_x":2168.6875,"label_y":703.0235748291016,"gene_reaction_rule":"","genes":[],"metabolites":[{"bigg_id":"U_E","coefficient":-1}],"segments":{"199":{"from_node_id":"212","to_node_id":"211","b1":null,"b2":null},"200":{"from_node_id":"213","to_node_id":"212","b1":null,"b2":null},"201":{"from_node_id":"210","to_node_id":"211","b1":{"x":2156.6875,"y":743.0235748291016},"b2":{"x":2102.4375,"y":743.0235748291016}}}}},"nodes":{"12":{"node_type":"metabolite","x":-241.0213623046875,"y":48.60261535644531,"bigg_id":"A_E","name":"Extracellular A","label_x":-257.2213623046875,"label_y":88.60261535644531,"node_is_primary":true},"13":{"node_type":"multimarker","x":-396.0209797328646,"y":48.94699468035586},"14":{"node_type":"midmarker","x":-416.0209303687584,"y":48.99143072215077},"15":{"node_type":"multimarker","x":-436.0208810046522,"y":49.03586676394568},"16":{"node_type":"metabolite","x":-243.77035522460938,"y":196.4971466064453,"bigg_id":"B_E","name":"Extracellular B","label_x":-259.97035522460936,"label_y":236.4971466064453,"node_is_primary":true},"17":{"node_type":"multimarker","x":-398.76997265278646,"y":196.84152593035589},"18":{"node_type":"midmarker","x":-418.7699232886803,"y":196.88596197215077},"19":{"node_type":"multimarker","x":-438.7698739245741,"y":196.9303980139457},"24":{"node_type":"metabolite","x":-249.26828002929688,"y":343.29209899902344,"bigg_id":"C_E","name":"Extracellular C","label_x":-265.46828002929686,"label_y":383.29209899902344,"node_is_primary":true},"25":{"node_type":"multimarker","x":-404.24257679434436,"y":346.114747078221},"26":{"node_type":"midmarker","x":-424.23926024789887,"y":346.47895973360136},"27":{"node_type":"multimarker","x":-444.2359437014534,"y":346.8431723889817},"28":{"node_type":"metabolite","x":-248.168701171875,"y":484.58912658691406,"bigg_id":"D_E","name":"Extracellular D","label_x":-264.368701171875,"label_y":524.5891265869141,"node_is_primary":true},"29":{"node_type":"multimarker","x":-403.1429979369225,"y":487.4117746661117},"30":{"node_type":"midmarker","x":-423.139681390477,"y":487.77598732149204},"31":{"node_type":"multimarker","x":-443.1363648440315,"y":488.1401999768723},"32":{"node_type":"metabolite","x":-250.19781494140625,"y":794.4128570556641,"bigg_id":"F_E","name":"Extracellular F","label_x":-266.39781494140624,"label_y":834.4128570556641,"node_is_primary":true},"33":{"node_type":"multimarker","x":-405.17211170645373,"y":797.2355051348617},"34":{"node_type":"midmarker","x":-425.16879516000824,"y":797.599717790242},"35":{"node_type":"multimarker","x":-445.16547861356275,"y":797.9639304456223},"40":{"node_type":"multimarker","x":-86.0213623046875,"y":48.60261535644531},"41":{"node_type":"midmarker","x":-66.0213623046875,"y":48.60261535644531},"42":{"node_type":"multimarker","x":-46.0213623046875,"y":48.60261535644531},"43":{"node_type":"metabolite","x":108.9786376953125,"y":48.60261535644531,"bigg_id":"A_C","name":"Cytosolic A","label_x":92.77863769531245,"label_y":88.60261535644531,"node_is_primary":true},"44":{"node_type":"multimarker","x":-88.77035522460938,"y":196.4971466064453},"45":{"node_type":"midmarker","x":-68.77035522460938,"y":196.4971466064453},"46":{"node_type":"multimarker","x":-48.770355224609375,"y":196.4971466064453},"47":{"node_type":"metabolite","x":106.22964477539062,"y":196.4971466064453,"bigg_id":"B_C","name":"Cytosolic B","label_x":90.02964477539058,"label_y":236.4971466064453,"node_is_primary":true},"48":{"node_type":"multimarker","x":-94.26828002929688,"y":343.29209899902344},"49":{"node_type":"midmarker","x":-74.26828002929688,"y":343.29209899902344},"50":{"node_type":"multimarker","x":-54.268280029296875,"y":343.29209899902344},"51":{"node_type":"metabolite","x":99.25222778320312,"y":343.2920684814453,"bigg_id":"C_C","name":"Cytosolic C","label_x":83.05222778320308,"label_y":383.2920684814453,"node_is_primary":true},"52":{"node_type":"multimarker","x":-93.168701171875,"y":484.58912658691406},"53":{"node_type":"midmarker","x":-73.168701171875,"y":484.58912658691406},"54":{"node_type":"multimarker","x":-53.168701171875,"y":484.58912658691406},"55":{"node_type":"metabolite","x":101.831298828125,"y":484.58912658691406,"bigg_id":"D_C","name":"Cytosolic D","label_x":85.63129882812495,"label_y":524.5891265869141,"node_is_primary":true},"56":{"node_type":"multimarker","x":-95.19781494140625,"y":794.4128570556641},"57":{"node_type":"midmarker","x":-75.19781494140625,"y":794.4128570556641},"58":{"node_type":"multimarker","x":-55.19781494140625,"y":794.4128570556641},"59":{"node_type":"metabolite","x":99.80218505859375,"y":794.4128570556641,"bigg_id":"F_C","name":"Cytosolic F","label_x":83.6021850585937,"label_y":834.4128570556641,"node_is_primary":true},"66":{"node_type":"multimarker","x":266.93731689453125,"y":48.60260009765625},"67":{"node_type":"midmarker","x":329.83843994140625,"y":48.60261535644531},"68":{"node_type":"multimarker","x":398.65692138671875,"y":48.60260772705078},"69":{"node_type":"metabolite","x":106.49053955078125,"y":196.6526641845703,"bigg_id":"B_C","name":"Cytosolic B","label_x":90.2905395507812,"label_y":236.6526641845703,"node_is_primary":true},"70":{"node_type":"metabolite","x":651.2940673828125,"y":45.6439208984375,"bigg_id":"G_C","name":"Cytosolic G","label_x":635.0940673828125,"label_y":85.6439208984375,"node_is_primary":true},"71":{"node_type":"metabolite","x":506.0424034071957,"y":176.6444660361842,"bigg_id":"H_C","name":"Cytosolic H","label_x":489.84240340719566,"label_y":216.6444660361842,"node_is_primary":true},"77":{"node_type":"metabolite","x":100.36334228515625,"y":343.7145538330078,"bigg_id":"C_C","name":"Cytosolic C","label_x":84.1633422851562,"label_y":383.7145538330078,"node_is_primary":true},"78":{"node_type":"multimarker","x":646.9200439453125,"y":287.3841094970703},"79":{"node_type":"midmarker","x":675.7962646484375,"y":287.38414001464844},"80":{"node_type":"multimarker","x":710.5897216796875,"y":285.90480041503906},"81":{"node_type":"metabolite","x":506.7135009765625,"y":176.43296813964844,"bigg_id":"H_C","name":"Cytosolic H","label_x":490.51350097656245,"label_y":216.43296813964844,"node_is_primary":true},"82":{"node_type":"metabolite","x":807.8951416015625,"y":285.90480041503906,"bigg_id":"I_C","name":"Cytosolic I","label_x":791.6951416015625,"label_y":325.90480041503906,"node_is_primary":true},"83":{"node_type":"multimarker","x":255.36334228515625,"y":423.59938049316406},"84":{"node_type":"midmarker","x":275.36334228515625,"y":423.59938049316406},"85":{"node_type":"multimarker","x":295.36334228515625,"y":423.59938049316406},"86":{"node_type":"metabolite","x":102.31329345703125,"y":484.3678741455078,"bigg_id":"D_C","name":"Cytosolic D","label_x":86.1132934570312,"label_y":524.3678741455078,"node_is_primary":true},"87":{"node_type":"metabolite","x":511.01666259765625,"y":425.07875061035156,"bigg_id":"J_C","name":"Cytosolic J","label_x":494.8166625976562,"label_y":465.07875061035156,"node_is_primary":true},"88":{"node_type":"metabolite","x":-244.795654296875,"y":643.9072418212891,"bigg_id":"E_E","name":"Extracellular E","label_x":-260.995654296875,"label_y":683.9072418212891,"node_is_primary":true},"89":{"node_type":"multimarker","x":-399.795654296875,"y":643.9072418212891},"90":{"node_type":"midmarker","x":-419.795654296875,"y":643.9072418212891},"91":{"node_type":"multimarker","x":-439.795654296875,"y":643.9072418212891},"92":{"node_type":"metabolite","x":-244.795654296875,"y":643.9072418212891,"bigg_id":"E_E","name":"Extracellular E","label_x":-260.995654296875,"label_y":683.9072418212891,"node_is_primary":true},"93":{"node_type":"multimarker","x":-89.795654296875,"y":643.9072418212891},"94":{"node_type":"midmarker","x":-69.795654296875,"y":643.9072418212891},"95":{"node_type":"multimarker","x":-49.795654296875,"y":643.9072418212891},"96":{"node_type":"metabolite","x":105.204345703125,"y":643.9072418212891,"bigg_id":"E_C","name":"Cytosolic E","label_x":89.00434570312495,"label_y":683.9072418212891,"node_is_primary":true},"97":{"node_type":"multimarker","x":260.204345703125,"y":643.9072418212891},"98":{"node_type":"midmarker","x":280.204345703125,"y":643.9072418212891},"99":{"node_type":"multimarker","x":300.204345703125,"y":643.9072418212891},"100":{"node_type":"metabolite","x":455.204345703125,"y":643.9072418212891,"bigg_id":"M_C","name":"Cytosolic M","label_x":439.00434570312495,"label_y":683.9072418212891,"node_is_primary":true},"101":{"node_type":"multimarker","x":577.65869140625,"y":740.0648956298828},"102":{"node_type":"midmarker","x":597.65869140625,"y":740.0648956298828},"103":{"node_type":"multimarker","x":617.65869140625,"y":740.0648956298828},"104":{"node_type":"metabolite","x":99.15185546875,"y":794.9159698486328,"bigg_id":"F_C","name":"Cytosolic F","label_x":82.95185546874995,"label_y":834.9159698486328,"node_is_primary":true},"105":{"node_type":"metabolite","x":822.95654296875,"y":743.0235748291016,"bigg_id":"N_C","name":"Cytosolic N","label_x":806.75654296875,"label_y":783.0235748291016,"node_is_primary":true},"106":{"node_type":"multimarker","x":822.95654296875,"y":824.0561676025391},"107":{"node_type":"midmarker","x":822.9564208984375,"y":847.0147857666016},"108":{"node_type":"multimarker","x":822.9564208984375,"y":867.0148468017578},"109":{"node_type":"metabolite","x":822.95654296875,"y":931.7744903564453,"bigg_id":"N_E","name":"Extracellular N","label_x":847.95654296875,"label_y":931.7744903564453,"node_is_primary":true},"110":{"node_type":"multimarker","x":822.95654296875,"y":1018.7245025634766},"111":{"node_type":"midmarker","x":822.95654296875,"y":1038.7245025634766},"112":{"node_type":"multimarker","x":822.95654296875,"y":1058.7245025634766},"113":{"node_type":"multimarker","x":651.2940673828125,"y":-60.59513854980469},"114":{"node_type":"midmarker","x":651.2940673828125,"y":-40.59513854980469},"115":{"node_type":"multimarker","x":651.2940673828125,"y":-20.595138549804688},"116":{"node_type":"metabolite","x":651.2940673828125,"y":-141.62769317626953,"bigg_id":"G_E","name":"Extracellular G","label_x":676.2940673828125,"label_y":-141.62769317626953,"node_is_primary":true},"117":{"node_type":"multimarker","x":651.2940673828125,"y":-216.74285125732422},"118":{"node_type":"midmarker","x":651.2940673828125,"y":-236.74285125732422},"119":{"node_type":"multimarker","x":651.2940673828125,"y":-256.7428512573242},"120":{"node_type":"multimarker","x":661.7135009765625,"y":176.43296813964844},"121":{"node_type":"midmarker","x":681.7135009765625,"y":176.43296813964844},"122":{"node_type":"multimarker","x":701.7135009765625,"y":176.43296813964844},"123":{"node_type":"metabolite","x":856.7135009765625,"y":176.43296813964844,"bigg_id":"K_C","name":"Cytosolic K","label_x":840.5135009765625,"label_y":216.43296813964844,"node_is_primary":true},"124":{"node_type":"multimarker","x":973.46044921875,"y":47.123260498046875},"125":{"node_type":"midmarker","x":993.46044921875,"y":47.123260498046875},"126":{"node_type":"multimarker","x":1013.46044921875,"y":47.123260498046875},"127":{"node_type":"metabolite","x":857.3941650390625,"y":175.94178771972656,"bigg_id":"K_C","name":"Cytosolic K","label_x":841.1941650390625,"label_y":215.94178771972656,"node_is_primary":true},"128":{"node_type":"metabolite","x":1116.6832275390625,"y":45.6439208984375,"bigg_id":"L_C","name":"Cytosolic L","label_x":1100.4832275390625,"label_y":85.6439208984375,"node_is_primary":true},"129":{"node_type":"multimarker","x":666.0166625976562,"y":425.07875061035156},"130":{"node_type":"midmarker","x":686.0166625976562,"y":425.07875061035156},"131":{"node_type":"multimarker","x":706.0166625976562,"y":425.07875061035156},"132":{"node_type":"metabolite","x":861.0166625976562,"y":425.07875061035156,"bigg_id":"Q_C","name":"Cytosolic Q","label_x":844.8166625976562,"label_y":465.07875061035156,"node_is_primary":true},"133":{"node_type":"multimarker","x":897.8037109375,"y":285.90480041503906},"134":{"node_type":"midmarker","x":917.8037109375,"y":285.90480041503906},"135":{"node_type":"multimarker","x":937.8037109375,"y":285.90480041503906},"136":{"node_type":"metabolite","x":1015.8775634765625,"y":284.4254608154297,"bigg_id":"P_C","name":"Cytosolic P","label_x":999.6775634765625,"label_y":324.4254608154297,"node_is_primary":true},"137":{"node_type":"multimarker","x":1157.5634765625,"y":361.35157775878906},"138":{"node_type":"midmarker","x":1177.5634765625,"y":361.35157775878906},"139":{"node_type":"multimarker","x":1197.5634765625,"y":361.35157775878906},"140":{"node_type":"metabolite","x":861.0164794921875,"y":425.07875061035156,"bigg_id":"Q_C","name":"Cytosolic Q","label_x":844.8164794921875,"label_y":465.07875061035156,"node_is_primary":true},"141":{"node_type":"metabolite","x":1333.33203125,"y":359.8722686767578,"bigg_id":"S_C","name":"Cytosolic S","label_x":1317.1320312500002,"label_y":399.8722686767578,"node_is_primary":true},"142":{"node_type":"multimarker","x":982.39453125,"y":738.5855255126953},"143":{"node_type":"midmarker","x":1002.39453125,"y":738.5855255126953},"144":{"node_type":"multimarker","x":1022.39453125,"y":738.5855255126953},"145":{"node_type":"metabolite","x":1693.6875,"y":743.0235748291016,"bigg_id":"U_C","name":"Cytosolic U","label_x":1677.4875000000002,"label_y":783.0235748291016,"node_is_primary":true},"146":{"node_type":"multimarker","x":1007.54345703125,"y":538.8733673095703},"147":{"node_type":"midmarker","x":1046.77490234375,"y":538.8734283447266},"148":{"node_type":"multimarker","x":1081.5684814453125,"y":537.3940582275391},"149":{"node_type":"metabolite","x":1335.6849365234375,"y":535.9147491455078,"bigg_id":"T_C","name":"Cytosolic T","label_x":1319.4849365234375,"label_y":575.9147491455078,"node_is_primary":true},"150":{"node_type":"multimarker","x":1271.6832275390625,"y":45.6439208984375},"151":{"node_type":"midmarker","x":1291.6832275390625,"y":45.6439208984375},"152":{"node_type":"multimarker","x":1311.6832275390625,"y":45.6439208984375},"153":{"node_type":"metabolite","x":1707.03955078125,"y":47.123268127441406,"bigg_id":"W_C","name":"Cytosolic W","label_x":1690.8395507812502,"label_y":87.1232681274414,"node_is_primary":true},"154":{"node_type":"multimarker","x":1843.5855712890625,"y":47.123268127441406},"155":{"node_type":"midmarker","x":1863.5855712890625,"y":47.123268127441406},"156":{"node_type":"multimarker","x":1883.5855712890625,"y":47.123268127441406},"157":{"node_type":"metabolite","x":2038.5855712890625,"y":47.123268127441406,"bigg_id":"W_E","name":"Extracellular W","label_x":2022.3855712890627,"label_y":87.1232681274414,"node_is_primary":true},"158":{"node_type":"multimarker","x":2193.5855712890625,"y":47.123268127441406},"159":{"node_type":"midmarker","x":2213.5855712890625,"y":47.123268127441406},"160":{"node_type":"multimarker","x":2233.5855712890625,"y":47.123268127441406},"161":{"node_type":"multimarker","x":925.112548828125,"y":175.94178771972656},"162":{"node_type":"midmarker","x":945.112548828125,"y":175.94178771972656},"163":{"node_type":"multimarker","x":965.112548828125,"y":175.94178771972656},"164":{"node_type":"metabolite","x":1040.2276611328125,"y":175.9418182373047,"bigg_id":"O_C","name":"Cytosolic O","label_x":1024.0276611328125,"label_y":215.9418182373047,"node_is_primary":true},"165":{"node_type":"multimarker","x":1218.897216796875,"y":178.90049743652344},"166":{"node_type":"midmarker","x":1268.484375,"y":178.90049743652344},"167":{"node_type":"multimarker","x":1315.112548828125,"y":177.42112731933594},"168":{"node_type":"metabolite","x":1014.070068359375,"y":284.04942321777344,"bigg_id":"P_C","name":"Cytosolic P","label_x":997.870068359375,"label_y":324.04942321777344,"node_is_primary":true},"169":{"node_type":"metabolite","x":1707.03955078125,"y":175.9417953491211,"bigg_id":"R_C","name":"Cytosolic R","label_x":1690.8395507812502,"label_y":215.9417953491211,"node_is_primary":true},"170":{"node_type":"multimarker","x":1818.9073486328125,"y":177.42113494873047},"171":{"node_type":"midmarker","x":1838.9073486328125,"y":177.42113494873047},"172":{"node_type":"multimarker","x":1858.9073486328125,"y":177.42113494873047},"173":{"node_type":"metabolite","x":2034.6180419921875,"y":180.37981414794922,"bigg_id":"R_E","name":"Extracellular R","label_x":2018.4180419921877,"label_y":220.37981414794922,"node_is_primary":true},"174":{"node_type":"multimarker","x":2194.0562744140625,"y":178.90050506591797},"175":{"node_type":"midmarker","x":2214.0562744140625,"y":178.90050506591797},"176":{"node_type":"multimarker","x":2234.0562744140625,"y":178.90050506591797},"177":{"node_type":"multimarker","x":1488.33203125,"y":359.8722686767578},"178":{"node_type":"midmarker","x":1508.33203125,"y":359.8722686767578},"179":{"node_type":"multimarker","x":1528.33203125,"y":359.8722686767578},"180":{"node_type":"metabolite","x":1335.281982421875,"y":536.0299224853516,"bigg_id":"T_C","name":"Cytosolic T","label_x":1319.081982421875,"label_y":576.0299224853516,"node_is_primary":true},"181":{"node_type":"metabolite","x":1707.03955078125,"y":364.31031799316406,"bigg_id":"V_C","name":"Cytosolic V","label_x":1690.8395507812502,"label_y":404.31031799316406,"node_is_primary":true},"182":{"node_type":"metabolite","x":1707.03955078125,"y":537.5093536376953,"bigg_id":"X_C","name":"Cytosolic X","label_x":1690.8395507812502,"label_y":577.5093536376953,"node_is_primary":true},"183":{"node_type":"multimarker","x":1862.03955078125,"y":364.31031799316406},"184":{"node_type":"midmarker","x":1882.03955078125,"y":364.31031799316406},"185":{"node_type":"multimarker","x":1902.03955078125,"y":364.31031799316406},"186":{"node_type":"metabolite","x":2057.03955078125,"y":364.31031799316406,"bigg_id":"V_E","name":"Extracellular V","label_x":2040.8395507812502,"label_y":404.31031799316406,"node_is_primary":true},"187":{"node_type":"multimarker","x":2212.03955078125,"y":364.31031799316406},"188":{"node_type":"midmarker","x":2232.03955078125,"y":364.31031799316406},"189":{"node_type":"multimarker","x":2252.03955078125,"y":364.31031799316406},"200":{"node_type":"multimarker","x":1862.03955078125,"y":537.5093536376953},"201":{"node_type":"midmarker","x":1882.03955078125,"y":537.5093536376953},"202":{"node_type":"multimarker","x":1902.03955078125,"y":537.5093536376953},"203":{"node_type":"metabolite","x":2057.03955078125,"y":537.5093536376953,"bigg_id":"X_E","name":"Extracellular X","label_x":2040.8395507812502,"label_y":577.5093536376953,"node_is_primary":true},"204":{"node_type":"multimarker","x":2212.03955078125,"y":537.5093536376953},"205":{"node_type":"midmarker","x":2232.03955078125,"y":537.5093536376953},"206":{"node_type":"multimarker","x":2252.03955078125,"y":537.5093536376953},"207":{"node_type":"multimarker","x":1848.6875,"y":743.0235748291016},"208":{"node_type":"midmarker","x":1868.6875,"y":743.0235748291016},"209":{"node_type":"multimarker","x":1888.6875,"y":743.0235748291016},"210":{"node_type":"metabolite","x":2043.6875,"y":743.0235748291016,"bigg_id":"U_E","name":"Extracellular U","label_x":2027.4875000000002,"label_y":783.0235748291016,"node_is_primary":true},"211":{"node_type":"multimarker","x":2198.6875,"y":743.0235748291016},"212":{"node_type":"midmarker","x":2218.6875,"y":743.0235748291016},"213":{"node_type":"multimarker","x":2238.6875,"y":743.0235748291016}},"text_labels":{},"canvas":{"x":-1920,"y":-919,"width":5760,"height":2757}}]